{
  "data": [
    {
      "id": "unit-000090",
      "title": {
        "ar": "دوبلكس 215 متر - التجمع الخامس",
        "en": "Duplex 215 sqm - Fifth Settlement"
      },
      "location": {
        "ar": "التجمع الخامس",
        "en": "Fifth Settlement"
      },
      "locationId": "fifth-settlement",
      "description": {
        "ar": "<p>دوبلكس فاخرة بمساحة 215 متر مربع في التجمع الخامس. تتميز بتشطيبات عالية الجودة وموقع متميز.</p>",
        "en": "<p>Luxury duplex with 215 sqm in Fifth Settlement. Features high-quality finishes and prime location.</p>"
      },
      "price": 2000000,
      "area": 215,
      "bedrooms": 3,
      "bathrooms": 3,
      "type": "duplex",
      "status": "active",
      "unitStatus": "reserved",
      "featured": false,
      "finishing": "core-shell",
      "paymentPlans": [
        "6-years"
      ],
      "features": {
        "ar": [
          "تراس واسع",
          "موقف سيارات",
          "حمام سباحة خاص",
          "تشطيب سوبر لوكس"
        ],
        "en": [
          "Near Transportation",
          "Parking",
          "Sea View",
          "Private Garden"
        ]
      },
      "images": [
        "/uploads/1766644120512-c9feca98-1331-4f41-bf53-a3825cddbb50.jpg",
        "/uploads/1766590847252-c1151886-0163-48e7-abe1-4dea0f2f3b68.jpg"
      ],
      "buildingNumber": "22",
      "floor": "الرابع",
      "unitNumber": "2053",
      "usableSpace": 183,
      "gardenShare": 0,
      "view": "",
      "projectId": "project-0015",
      "createdAt": "2025-12-27T03:44:50.107Z",
      "createdBy": "admin-001",
      "updatedAt": "2025-12-27T03:44:50.107Z"
    },
    {
      "id": "unit-000112",
      "title": {
        "ar": "تاون هاوس 353 متر - جولف بورتو مارينا",
        "en": "Townhouse 353 sqm - Golf Porto Marina"
      },
      "location": {
        "ar": "جولف بورتو مارينا",
        "en": "Golf Porto Marina"
      },
      "locationId": "golf-porto-marina",
      "description": {
        "ar": "<p>تاون هاوس فاخرة بمساحة 353 متر مربع في جولف بورتو مارينا. تتميز بتشطيبات عالية الجودة وموقع متميز.</p>",
        "en": "<p>Luxury townhouse with 353 sqm in Golf Porto Marina. Features high-quality finishes and prime location.</p>"
      },
      "price": 2000000,
      "area": 353,
      "bedrooms": 4,
      "bathrooms": 3,
      "type": "townhouse",
      "status": "active",
      "unitStatus": "available",
      "featured": false,
      "finishing": "core-shell",
      "paymentPlans": [
        "cash",
        "8-years"
      ],
      "features": {
        "ar": [
          "قريب من المواصلات",
          "نادي رياضي",
          "أمن 24 ساعة"
        ],
        "en": [
          "Maid Room",
          "Central AC",
          "Parking",
          "Sea View",
          "Premium Finish"
        ]
      },
      "images": [
        "/uploads/1766644392683-f80be205-732f-4692-b953-5db73e48a436.jpg"
      ],
      "buildingNumber": "39",
      "floor": "الرابع",
      "unitNumber": "286",
      "usableSpace": 300,
      "gardenShare": 115,
      "view": "pool",
      "projectId": "project-0019",
      "createdAt": "2025-12-27T03:44:50.216Z",
      "createdBy": "admin-001",
      "updatedAt": "2025-12-27T03:44:50.216Z"
    },
    {
      "id": "unit-000232",
      "title": {
        "ar": "شاليه 96 متر - العين السخنة",
        "en": "Chalet 96 sqm - Ain Sokhna"
      },
      "location": {
        "ar": "العين السخنة",
        "en": "Ain Sokhna"
      },
      "locationId": "ain-sokhna",
      "description": {
        "ar": "<p>شاليه فاخرة بمساحة 96 متر مربع في العين السخنة. تتميز بتشطيبات عالية الجودة وموقع متميز.</p>",
        "en": "<p>Luxury chalet with 96 sqm in Ain Sokhna. Features high-quality finishes and prime location.</p>"
      },
      "price": 2000000,
      "area": 96,
      "bedrooms": 2,
      "bathrooms": 1,
      "type": "chalet",
      "status": "active",
      "unitStatus": "sold",
      "featured": false,
      "finishing": "finished",
      "paymentPlans": [
        "10-years",
        "cash"
      ],
      "features": {
        "ar": [
          "غرفة خادمة",
          "إطلالة بحرية",
          "تشطيب سوبر لوكس"
        ],
        "en": [
          "Premium Finish",
          "Private Pool",
          "Private Garden",
          "Gym",
          "Parking",
          "Private Elevator"
        ]
      },
      "images": [
        "/uploads/1766644120512-c9feca98-1331-4f41-bf53-a3825cddbb50.jpg",
        "/uploads/1766644392683-f80be205-732f-4692-b953-5db73e48a436.jpg"
      ],
      "buildingNumber": "45",
      "floor": "الخامس",
      "unitNumber": "5722",
      "usableSpace": 82,
      "gardenShare": 0,
      "view": "sea",
      "projectId": "project-0025",
      "createdAt": "2025-12-27T03:44:51.182Z",
      "createdBy": "admin-001",
      "updatedAt": "2025-12-27T03:44:51.182Z"
    }
  ],
  "total": 3,
  "page": 1,
  "limit": 20,
  "totalPages": 1,
  "hasNext": false,
  "hasPrev": false,
  "filter": {
    "price": "2000000"
  },
  "generatedAt": "2025-12-27T22:58:12.084Z"
}